rlbot_twitch_broker_client/__init__.py
rlbot_twitch_broker_client/api_client.py
rlbot_twitch_broker_client/configuration.py
rlbot_twitch_broker_client/defaults.py
rlbot_twitch_broker_client/rest.py
rlbot_twitch_broker_client/api/__init__.py
rlbot_twitch_broker_client/api/chat_api.py
rlbot_twitch_broker_client/api/register_api.py
rlbot_twitch_broker_client/api/static_api.py
rlbot_twitch_broker_client/models/__init__.py
rlbot_twitch_broker_client/models/action_server_registration.py
rlbot_twitch_broker_client/models/api_response.py
rlbot_twitch_broker_client/models/chat_line.py
test/__init__.py
test/test_action_server_registration.py
test/test_api_response.py
test/test_chat_api.py
test/test_chat_line.py
test/test_register_api.py
test/test_static_api.py
rlbot_twitch_broker_client-1.0.0.dist-info/METADATA
rlbot_twitch_broker_client-1.0.0.dist-info/WHEEL
rlbot_twitch_broker_client-1.0.0.dist-info/top_level.txt
rlbot_twitch_broker_client-1.0.0.dist-info/RECORD
